coloraide/__init__.py
coloraide/__meta__.py
coloraide/algebra.py
coloraide/average.py
coloraide/cat.py
coloraide/channels.py
coloraide/cmfs.py
coloraide/color.py
coloraide/convert.py
coloraide/deprecate.py
coloraide/easing.py
coloraide/everything.py
coloraide/harmonies.py
coloraide/py.typed
coloraide/types.py
coloraide/util.py
coloraide/compositing/__init__.py
coloraide/compositing/blend_modes.py
coloraide/compositing/porter_duff.py
coloraide/contrast/__init__.py
coloraide/contrast/lstar.py
coloraide/contrast/wcag21.py
coloraide/css/__init__.py
coloraide/css/color_names.py
coloraide/css/parse.py
coloraide/css/serialize.py
coloraide/distance/__init__.py
coloraide/distance/delta_e_2000.py
coloraide/distance/delta_e_76.py
coloraide/distance/delta_e_94.py
coloraide/distance/delta_e_99o.py
coloraide/distance/delta_e_cam02.py
coloraide/distance/delta_e_cam16.py
coloraide/distance/delta_e_cmc.py
coloraide/distance/delta_e_hct.py
coloraide/distance/delta_e_hyab.py
coloraide/distance/delta_e_itp.py
coloraide/distance/delta_e_ok.py
coloraide/distance/delta_e_z.py
coloraide/filters/__init__.py
coloraide/filters/cvd.py
coloraide/filters/w3c_filter_effects.py
coloraide/gamut/__init__.py
coloraide/gamut/fit_hct_chroma.py
coloraide/gamut/fit_lch_chroma.py
coloraide/gamut/fit_minde_chroma.py
coloraide/gamut/fit_oklch_chroma.py
coloraide/gamut/fit_raytrace.py
coloraide/gamut/pointer.py
coloraide/gamut/tools.py
coloraide/interpolate/__init__.py
coloraide/interpolate/bspline.py
coloraide/interpolate/bspline_natural.py
coloraide/interpolate/catmull_rom.py
coloraide/interpolate/continuous.py
coloraide/interpolate/css_linear.py
coloraide/interpolate/linear.py
coloraide/interpolate/monotone.py
coloraide/spaces/__init__.py
coloraide/spaces/a98_rgb.py
coloraide/spaces/a98_rgb_linear.py
coloraide/spaces/aces2065_1.py
coloraide/spaces/acescc.py
coloraide/spaces/acescct.py
coloraide/spaces/acescg.py
coloraide/spaces/cam02.py
coloraide/spaces/cam02_ucs.py
coloraide/spaces/cam16.py
coloraide-8.0.dist-info/METADATA
coloraide-8.0.dist-info/WHEEL
coloraide-8.0.dist-info/licenses/LICENSE.md
coloraide-8.0.dist-info/RECORD
